pydantic_fixedwidth/__init__.py
pydantic_fixedwidth/fixedwidth.py
pydantic_fixedwidth/py.typed
pydantic_fixedwidth-0.2.2.dist-info/METADATA
pydantic_fixedwidth-0.2.2.dist-info/WHEEL
pydantic_fixedwidth-0.2.2.dist-info/licenses/LICENSE
pydantic_fixedwidth-0.2.2.dist-info/RECORD
