Metadata-Version: 2.4
Name: pydantic-fixedwidth
Version: 0.2.2
Summary: Custom Pydantic models for parsing and serializing fixed-width format of data.
Project-URL: Homepage, https://github.com/lasuillard/pydantic-fixedwidth
Project-URL: Repository, https://github.com/lasuillard/pydantic-fixedwidth.git
Project-URL: Issues, https://github.com/lasuillard/pydantic-fixedwidth/issues
License-Expression: MIT
License-File: LICENSE
Requires-Python: <4.0,>=3.9
Requires-Dist: pydantic<3,>=2
